Emsys CW/Labs/lab4/task1/alu.sv
// emsys_alu : a simple ALU-like unit for the lab4 of the EmSys course 
//

module alu (
        // Inputs
	input logic [7:0] a,
	input logic [7:0] b,

	input logic [2:0] op,

        // Outputs
	output logic [7:0] q
);
// -------------------------------

always_comb begin
	case (op)
		3'b000: q = a + b;
		3'b001: q = a - b;
		3'b010: q = (a >> 1);
		3'b100: q = a & b;
		3'b011: q = (a << 1);
		3'b101: q = a | b;

		default: q = 0;

	endcase

end

endmodule

Emsys CW/Labs/lab4/task1/top_tb.sv
// Busses and Muxes Testbench
//
// author: stf

module top_tb(
    input clk,
    input rst,

    input logic [7:0] a_in,
    input logic [7:0] b_in,
    input logic [2:0] op_in,

    output logic [7:0] q_out
);

   alu alu_inst(
	// inputs
        .a(a_in),
        .b(b_in),
        .op(op_in),
	
	// outputs
        .q(q_out)
   );

   always_ff @(posedge clk) begin 
        $display("opcode=%b, a=%d, b=%d, q=%d ", op_in, a_in, b_in, q_out);
   end


   // Print some stuff as an example
   initial begin
      if ($test$plusargs("trace") != 0) begin
         $display("[%0t] Tracing to logs/vlt_dump.vcd...\n", $time);
         $dumpfile("logs/vlt_dump.vcd");
         $dumpvars();
      end
      $display("[%0t] Model running...\n", $time);
   end

endmodule

Emsys CW/Labs/lab4/task1/wavedump.vcd
$version Generated by VerilatedVcd $end
$date Wed Nov 17 09:52:01 2021
 $end
$timescale   1ps $end

 $scope module TOP $end
  $var wire  8 % a_in [7:0] $end
  $var wire  8 & b_in [7:0] $end
  $var wire  1 # clk $end
  $var wire  3 ' op_in [2:0] $end
  $var wire  8 ( q_out [7:0] $end
  $var wire  1 $ rst $end
  $scope module top_tb $end
   $var wire  8 % a_in [7:0] $end
   $var wire  8 & b_in [7:0] $end
   $var wire  1 # clk $end
   $var wire  3 ' op_in [2:0] $end
   $var wire  8 ( q_out [7:0] $end
   $var wire  1 $ rst $end
   $scope module alu_inst $end
    $var wire  8 % a [7:0] $end
    $var wire  8 & b [7:0] $end
    $var wire  3 ' op [2:0] $end
    $var wire  8 ( q [7:0] $end
   $upscope $end
  $upscope $end
 $upscope $end
$enddefinitions $end


#1
1#
0$
b11011110 %
b10010001 &
b011 '
b10111100 (
#2
0#
b00000000 %
b00000001 &
b000 '
b00000001 (
#3
1#
#4
0#
b00101010 %
b00000010 &
b001 '
b00101000 (
#5
1#
#6
0#
b00010000 %
b00000000 &
b010 '
b00001000 (
#7
1#
#8
0#
b00001000 %
b011 '
b00010000 (
#9
1#
#10
0#
b11111111 %
b00000100 &
b100 '
b00000100 (
#11
1#
#12
0#
b00000001 %
b00000010 &
b101 '
b00000011 (
#13
1#
#14
0#
b00000010 %
b00000100 &
b00000110 (
