Emsys CW/Labs/lab4/task2/logs/annotated/alu.sv
	// verilator_coverage annotation
	// emsys_alu : a simple ALU-like unit for the lab4 of the EmSys course 
	//
	
	module alu (
 000022	    input clk,
%000003	    input rst,
	
	    // Inputs
%000019		input logic [7:0] a,
%000006		input logic [7:0] b,	
%000011		input logic [2:0] op,
	
	    // Outputs
%000040		output logic [7:0] q
	);
	// -------------------------------
	
%000025	logic [7:0] w;
%000042	logic [7:0] w_new;
 000048	logic [7:0] add;
 000050	logic [7:0] sub;
%000019	logic [7:0] sr1;
%000026	logic [7:0] sl1;
%000015	logic [7:0] and1;
%000027	logic [7:0] or1;
%000019	logic [7:0] set;
%000025	logic [7:0] unchanged; 
	
	assign add = w + a;
	assign sub  = w - a;
	assign sr1  = (w>>1);
	assign sl1  = (w<<1);
	assign and1  = w & a;
	assign or1  = w | a;
	assign set = a;
	assign unchanged  = w;
	
 000022	always_ff @(posedge clk) begin
 000011	    w <= w_new;
	
%000008	    if(rst) begin
%000007	    verilator_coverage: (next point on previous line)

%000004		    w <= 8'b0;
	    end
	
	end
	
	
		
 000050	always_comb begin
 000025		case(op)
%000008		       3'b000: w_new = add; 
%000004		       3'b001: w_new = sub;
%000004		       3'b010: w_new = sr1;
 000030		       3'b011: w_new = sl1;
%000000		       3'b100: w_new = and1;
%000000		       3'b101: w_new = or1;
%000004		       3'b110: w_new = set;
%000000		       3'b111: w_new = unchanged;
		       
	      endcase
		
	end
	
 000050	always_comb begin
%000004	    if(op == 3'b110) begin
%000002		    q = 8'd0;
	    end
%000000		else if (op == 3'b111) begin
 000023		verilator_coverage: (next point on previous line)

%000000			    q = 8'd0;
		    end 
 000023		    else begin
 000023		    q = w_new;
	    end 
	  
	    
		
	end
	
	endmodule

Emsys CW/Labs/lab4/task2/logs/annotated/top_tb.sv
	// verilator_coverage annotation
	// Busses and Muxes Testbench
	//
	// author: stf
	
	module top_tb(
 000022	    input clk,
%000003	    input rst,
	
%000019	    input logic [7:0] a_in,
%000006	    input logic [7:0] b_in,
%000011	    input logic [2:0] op_in,
	
%000040	    output logic [7:0] q_out
	);
	
	   alu alu_inst(
	        .clk(clk),
	        .rst(rst),
		// inputs
	        .a(a_in),
	        .b(b_in),
	        .op(op_in),
		
		// outputs
	        .q(q_out)
	   );
	
 000022	   always_ff @(posedge clk) begin 
%000014	        if(!rst) begin
%000004	        verilator_coverage: (next point on previous line)

%000007	                $display("opcode=%b, a=%d, b=%d, q=%d ", op_in, a_in, b_in, q_out);
	        end
	   end
	
	
	   // Print some stuff as an example
%000002	   initial begin
%000002	      if ($test$plusargs("trace") != 0) begin
%000000	      verilator_coverage: (next point on previous line)

%000001	         $display("[%0t] Tracing to logs/vlt_dump.vcd...\n", $time);
%000001	         $dumpfile("logs/vlt_dump.vcd");
%000001	         $dumpvars();
	      end
%000001	      $display("[%0t] Model running...\n", $time);
	   end
	
	endmodule

Emsys CW/Labs/lab4/task2/logs/vlt_dump.vcd
$version Generated by VerilatedVcd $end
$date Wed Nov 17 16:09:45 2021
 $end
$timescale   1ps $end

 $scope module TOP $end
  $var wire  8 - a_in [7:0] $end
  $var wire  8 . b_in [7:0] $end
  $var wire  1 + clk $end
  $var wire  3 / op_in [2:0] $end
  $var wire  8 0 q_out [7:0] $end
  $var wire  1 , rst $end
  $scope module top_tb $end
   $var wire  8 - a_in [7:0] $end
   $var wire  8 . b_in [7:0] $end
   $var wire  1 + clk $end
   $var wire  3 / op_in [2:0] $end
   $var wire  8 0 q_out [7:0] $end
   $var wire  1 , rst $end
   $scope module alu_inst $end
    $var wire  8 - a [7:0] $end
    $var wire  8 $ add [7:0] $end
    $var wire  8 & and1 [7:0] $end
    $var wire  8 . b [7:0] $end
    $var wire  1 + clk $end
    $var wire  3 / op [2:0] $end
    $var wire  8 ' or1 [7:0] $end
    $var wire  8 0 q [7:0] $end
    $var wire  1 , rst $end
    $var wire  8 - set [7:0] $end
    $var wire  8 * sl1 [7:0] $end
    $var wire  8 ) sr1 [7:0] $end
    $var wire  8 % sub [7:0] $end
    $var wire  8 ( unchanged [7:0] $end
    $var wire  8 ( w [7:0] $end
    $var wire  8 # w_new [7:0] $end
   $upscope $end
  $upscope $end
 $upscope $end
$enddefinitions $end


#1
b01001010 #
b00000011 $
b01000111 %
b00000100 &
b11111111 '
b00100101 (
b00010010 )
b01001010 *
1+
0,
b11011110 -
b10010001 .
b011 /
b01001010 0
#2
0+
1,
#3
b00000000 #
b11011110 $
b00100010 %
b00000000 &
b11011110 '
b00000000 (
b00000000 )
b00000000 *
1+
b00000000 0
#4
0+
#5
1+
#6
0+
#7
1+
#8
0+
#9
1+
#10
b00001010 #
b00001010 $
b11110110 %
b00001010 '
0+
0,
b00001010 -
b00000000 .
b110 /
#11
b00010100 $
b00000000 %
b00001010 &
b00001010 (
b00000101 )
b00010100 *
1+
#12
b00001011 #
b00001011 $
b00001001 %
b00000000 &
b00001011 '
0+
b00000001 -
b000 /
b00001011 0
#13
b00001100 #
b00001100 $
b00001010 %
b00000001 &
b00001011 (
b00010110 *
1+
b00001100 0
#14
b00001001 #
b00001101 $
b00001001 %
b00000010 &
0+
b00000010 -
b001 /
b00001001 0
#15
b00000111 #
b00001011 $
b00000111 %
b00000000 &
b00001001 (
b00000100 )
b00010010 *
1+
b00000111 0
#16
b00010010 #
b00001001 $
b00001001 %
b00001001 '
0+
b00000000 -
b011 /
b00010010 0
#17
b00100100 #
b00010010 $
b00010010 %
b00010010 '
b00010010 (
b00001001 )
b00100100 *
1+
b00100100 0
#18
b00001001 #
0+
b010 /
b00001001 0
#19
b00000100 #
b00001001 $
b00001001 %
b00001001 '
b00001001 (
b00000100 )
b00010010 *
1+
b00000100 0
#20
b00001100 #
b00001100 $
b00000110 %
b00000001 &
b00001011 '
0+
b00000011 -
b000 /
b00001100 0
#21
b00001111 #
b00001111 $
b00001001 %
b00000000 &
b00001111 '
b00001100 (
b00000110 )
b00011000 *
1+
b00001111 0
#22
b00011000 #
b00001100 $
b00001100 %
b00001100 '
0+
b00000000 -
b011 /
b00011000 0
#23
b00110000 #
b00011000 $
b00011000 %
b00011000 '
b00011000 (
b00001100 )
b00110000 *
1+
b00110000 0
